README.md
nyaraka.py
setup.py
nyaraka.egg-info/PKG-INFO
nyaraka.egg-info/SOURCES.txt
nyaraka.egg-info/dependency_links.txt
nyaraka.egg-info/requires.txt
nyaraka.egg-info/top_level.txt