Metadata-Version: 1.0
Name: nyaraka
Version: 0.0.2
Summary: Download Omeka data
Home-page: http://github.com/edsu/nyaraka
Author: Ed Summers
Author-email: ehs@pobox.com
License: UNKNOWN
Platform: UNKNOWN
